README.md
setup.py
BaiduImageSpider/BaiduImageSpider.py
BaiduImageSpider/__init__.py
BaiduImageSpider.egg-info/PKG-INFO
BaiduImageSpider.egg-info/SOURCES.txt
BaiduImageSpider.egg-info/dependency_links.txt
BaiduImageSpider.egg-info/top_level.txt