Metadata-Version: 2.1
Name: BaiduImageSpider
Version: 0.0.1
Summary: This is a package for searching for pictures on Baidu with keywords.
Home-page: https://github.com/fuweifu-vtoo/BaiduImageSpider.git
Author: fuweifu
Author-email: 1360004212@qq.com
License: UNKNOWN
Platform: UNKNOWN
